AUTHORS
LICENSE
MANIFEST.in
README
VERSION
setup.py
ricerca/__init__.py
ricerca/content.py
ricerca.egg-info/PKG-INFO
ricerca.egg-info/SOURCES.txt
ricerca.egg-info/dependency_links.txt
ricerca.egg-info/requires.txt
ricerca.egg-info/top_level.txt