Metadata-Version: 1.1
Name: ricerca
Version: 1.1.3
Summary: Content-based search based using FALCON: Feedback Adaptive Loop for Content-Based Retrieval
Home-page: http://murphylab.web.cmu.edu/software/ricerca
Author: Ivan Cao-Berg
Author-email: icaoberg@andrew.cmu.edu
License: UNKNOWN
Platform: UNKNOWN
Classifier: Programming Language :: Python
Classifier: Intended Audience :: Science/Research
Classifier: Intended Audience :: Developers
Classifier: Topic :: Scientific/Engineering
Classifier: Topic :: Database
Classifier: License :: OSI Approved :: GNU General Public License (GPL)
Classifier: Operating System :: OS Independent
Classifier: Programming Language :: Python
